color_aruco/__init__.py
color_aruco/aruco_marker_detect.py
color_aruco/aruco_marker_generator.py
color_aruco-0.1.0.0.dist-info/LICENSE
color_aruco-0.1.0.0.dist-info/METADATA
color_aruco-0.1.0.0.dist-info/WHEEL
color_aruco-0.1.0.0.dist-info/top_level.txt
color_aruco-0.1.0.0.dist-info/RECORD
