Metadata-Version: 2.1
Name: color_aruco
Version: 0.1.0.0
Summary: A package to detect colored ArUco markers.
Home-page: https://github.com/AydenBravender/color_aruco
Author: Ayden Bravender
Author-email: aydenbravender@gmail.com
Project-URL: Bug Tracker, https://github.com/AydenBravender/color_aruco/issues
Classifier: Programming Language :: Python :: 3
Classifier: License :: OSI Approved :: MIT License
Classifier: Operating System :: OS Independent
Requires-Python: >=3.6
License-File: LICENSE
Requires-Dist: numpy
Requires-Dist: opencv-python
Requires-Dist: opencv-contrib-python
